<fsm start='INIT' inputDecoding='UTF-8' outputEncoding='UTF-8'>
<e> <s>INIT</s> <in>A1</in> <out>Ā</out> </e>
<e> <s>INIT</s> <in>B1</in> <out>B1</out> </e>
<e> <s>INIT</s> <in>B2</in> <out>B2</out> </e>
<e> <s>INIT</s> <in>E4</in> <out>É</out> </e>
<e> <s>INIT</s> <in>I1</in> <out>Ī</out> </e>
<e> <s>INIT</s> <in>a1</in> <out>ā</out> </e>
<e> <s>INIT</s> <in>a10</in> <out>â</out> </e>
<e> <s>INIT</s> <in>a11</in> <out>à</out> </e>
<e> <s>INIT</s> <in>a111</in> <out>ā̀</out> </e>
<e> <s>INIT</s> <in>a12</in> <out>ā2</out> </e>
<e> <s>INIT</s> <in>a13</in> <out>ā3</out> </e>
<e> <s>INIT</s> <in>a14</in> <out>ā́</out> </e>
<e> <s>INIT</s> <in>a15</in> <out>ā5</out> </e>
<e> <s>INIT</s> <in>a16</in> <out>ā6</out> </e>
<e> <s>INIT</s> <in>a17</in> <out>ā7</out> </e>
<e> <s>INIT</s> <in>a2</in> <out>a2</out> </e>
<e> <s>INIT</s> <in>a3</in> <out>a3</out> </e>
<e> <s>INIT</s> <in>a4</in> <out>á</out> </e>
<e> <s>INIT</s> <in>a42</in> <out>á2</out> </e>
<e> <s>INIT</s> <in>a5</in> <out>a5</out> </e>
<e> <s>INIT</s> <in>a6</in> <out>a6</out> </e>
<e> <s>INIT</s> <in>a7</in> <out>ä</out> </e>
<e> <s>INIT</s> <in>c1</in> <out>c1</out> </e>
<e> <s>INIT</s> <in>c2</in> <out>c2</out> </e>
<e> <s>INIT</s> <in>c3</in> <out>c3</out> </e>
<e> <s>INIT</s> <in>d2</in> <out>ḍ</out> </e>
<e> <s>INIT</s> <in>d3</in> <out>d3</out> </e>
<e> <s>INIT</s> <in>d4</in> <out>d4</out> </e>
<e> <s>INIT</s> <in>d5</in> <out>d5</out> </e>
<e> <s>INIT</s> <in>e1</in> <out>ē</out> </e>
<e> <s>INIT</s> <in>e10</in> <out>ê</out> </e>
<e> <s>INIT</s> <in>e11</in> <out>è</out> </e>
<e> <s>INIT</s> <in>e2</in> <out>e2</out> </e>
<e> <s>INIT</s> <in>e4</in> <out>é</out> </e>
<e> <s>INIT</s> <in>e5</in> <out>ē</out> </e>
<e> <s>INIT</s> <in>e7</in> <out>ë</out> </e>
<e> <s>INIT</s> <in>e74</in> <out>ë́</out> </e>
<e> <s>INIT</s> <in>h1</in> <out>h1</out> </e>
<e> <s>INIT</s> <in>h2</in> <out>ḥ</out> </e>
<e> <s>INIT</s> <in>h3</in> <out>h3</out> </e>
<e> <s>INIT</s> <in>h4</in> <out>h4</out> </e>
<e> <s>INIT</s> <in>h5</in> <out>h5</out> </e>
<e> <s>INIT</s> <in>i1</in> <out>ī</out> </e>
<e> <s>INIT</s> <in>i10</in> <out>î</out> </e>
<e> <s>INIT</s> <in>i11</in> <out>ì</out> </e>
<e> <s>INIT</s> <in>i111</in> <out>ī̀</out> </e>
<e> <s>INIT</s> <in>i14</in> <out>ī́</out> </e>
<e> <s>INIT</s> <in>i2</in> <out>i2</out> </e>
<e> <s>INIT</s> <in>i3</in> <out>i3</out> </e>
<e> <s>INIT</s> <in>i4</in> <out>í</out> </e>
<e> <s>INIT</s> <in>i5</in> <out>i5</out> </e>
<e> <s>INIT</s> <in>i7</in> <out>ï</out> </e>
<e> <s>INIT</s> <in>j2</in> <out>j2</out> </e>
<e> <s>INIT</s> <in>j3</in> <out>j3</out> </e>
<e> <s>INIT</s> <in>j5</in> <out>j5</out> </e>
<e> <s>INIT</s> <in>l2</in> <out>ḷ</out> </e>
<e> <s>INIT</s> <in>l6</in> <out>ḻ</out> </e>
<e> <s>INIT</s> <in>m1</in> <out>m1</out> </e>
<e> <s>INIT</s> <in>m2</in> <out>m2</out> </e>
<e> <s>INIT</s> <in>m4</in> <out>m4</out> </e>
<e> <s>INIT</s> <in>n2</in> <out>ṇ</out> </e>
<e> <s>INIT</s> <in>n4</in> <out>n4</out> </e>
<e> <s>INIT</s> <in>n5</in> <out>ñ</out> </e>
<e> <s>INIT</s> <in>o10</in> <out>ô</out> </e>
<e> <s>INIT</s> <in>o11</in> <out>ò</out> </e>
<e> <s>INIT</s> <in>o3</in> <out>o3</out> </e>
<e> <s>INIT</s> <in>o4</in> <out>ó</out> </e>
<e> <s>INIT</s> <in>o42</in> <out>ó2</out> </e>
<e> <s>INIT</s> <in>o5</in> <out>ō</out> </e>
<e> <s>INIT</s> <in>o7</in> <out>ö</out> </e>
<e> <s>INIT</s> <in>r2</in> <out>ṛ</out> </e>
<e> <s>INIT</s> <in>r22</in> <out>ṛ2</out> </e>
<e> <s>INIT</s> <in>r23</in> <out>ṛ3</out> </e>
<e> <s>INIT</s> <in>r24</in> <out>ṛ́</out> </e>
<e> <s>INIT</s> <in>r25</in> <out>ṛ5</out> </e>
<e> <s>INIT</s> <in>r26</in> <out>ṛ6</out> </e>
<e> <s>INIT</s> <in>r28</in> <out>ṛ8</out> </e>
<e> <s>INIT</s> <in>r29</in> <out>ṛ9</out> </e>
<e> <s>INIT</s> <in>r3</in> <out>r3</out> </e>
<e> <s>INIT</s> <in>r9</in> <out>ṝ</out> </e>
<e> <s>INIT</s> <in>s2</in> <out>ṣ</out> </e>
<e> <s>INIT</s> <in>s22</in> <out>ṣ2</out> </e>
<e> <s>INIT</s> <in>s3</in> <out>s3</out> </e>
<e> <s>INIT</s> <in>s4</in> <out>s4</out> </e>
<e> <s>INIT</s> <in>t2</in> <out>ṭ</out> </e>
<e> <s>INIT</s> <in>t3</in> <out>t3</out> </e>
<e> <s>INIT</s> <in>t4</in> <out>t4</out> </e>
<e> <s>INIT</s> <in>t5</in> <out>t5</out> </e>
<e> <s>INIT</s> <in>t7</in> <out>t7</out> </e>
<e> <s>INIT</s> <in>u1</in> <out>ū</out> </e>
<e> <s>INIT</s> <in>u11</in> <out>ù</out> </e>
<e> <s>INIT</s> <in>u14</in> <out>ū́</out> </e>
<e> <s>INIT</s> <in>u2</in> <out>u2</out> </e>
<e> <s>INIT</s> <in>u3</in> <out>u3</out> </e>
<e> <s>INIT</s> <in>u4</in> <out>ú</out> </e>
<e> <s>INIT</s> <in>u42</in> <out>ú2</out> </e>
<e> <s>INIT</s> <in>u7</in> <out>ü</out> </e>
<e> <s>INIT</s> <in>y1</in> <out>ȳ</out> </e>
<!-- changed
<e> <s>INIT</s> <in>m3</in> <out>ṁ</out> </e>
-->
<e> <s>INIT</s> <in>m3</in> <out>ṃ</out> </e>
<e> <s>INIT</s> <in>Sam2hit</in> <out>Saṃhit</out> </e>  <!-- 1 case -->
<e> <s>INIT</s> <in>yad2@</in> <out>yad2@</out> </e>  <!-- 1 case -->
<e> <s>INIT</s> <in>vid2@</in> <out>vid2@</out> </e>  <!-- 1 case -->

<!--  other changes 
<e> <s>INIT</s> <in></in> <out></out> </e>
-->
<e> <s>INIT</s> <in>£</in> <out>√</out> </e>
<e> <s>INIT</s> <in></in> <out></out> </e>
<e> <s>INIT</s> <in>ç</in> <out>ś</out> </e>
<e> <s>INIT</s> <in>Ç</in> <out>Ś</out> </e>
<!-- typo at line 22522 <p>{@9.@}... -->
<e> <s>INIT</s> <in>•</in> <out></out> </e> 

<!-- diphthongs
 Āi -> Ai ,  āi -> ai 
 Āu -> Au ,  āu -> au

-->
<e> <s>INIT</s> <in>A1i</in> <out>Ai</out> </e>
<e> <s>INIT</s> <in>A1u</in> <out>Au</out> </e>
<e> <s>INIT</s> <in>a1i</in> <out>ai</out> </e>
<e> <s>INIT</s> <in>a1u</in> <out>au</out> </e>
<!-- accented diphthongs.  67 cases -->
<e> <s>INIT</s> <in>a1i4</in> <out>aí</out> </e>
<e> <s>INIT</s> <in>a1u4</in> <out>aú</out> </e>

<!-- nasal corrections
n3ç print ṅç SLP1=MS  IAST=ṃś  44 cases
n3s print ṅs SLP1=Ms  IAST=ṃs 124 cases
n3s2 print ṅṣ SLP1=Mz IAST=ṃṣ   8 cases
n3h  print ṅh SLP1=Mh IAST=ṃh  31 cases

<e> <s>INIT</s> <in>n3</in> <out>ṅ</out> </e>
  Change to anusvAra
-->
<e> <s>INIT</s> <in>n3ç</in> <out>ṃś</out> </e> 
<e> <s>INIT</s> <in>n3s</in> <out>ṃs</out> </e>
<e> <s>INIT</s> <in>n3s2</in> <out>ṃṣ</out> </e>
<e> <s>INIT</s> <in>n3h</in> <out>ṃh</out> </e>
<e> <s>INIT</s> <in>n3</in> <out>ṃ</out> </e>
<!-- exceptions : homophone number-->
<e> <s>INIT</s> <in>an3,@}</in> <out>an3,@}</out> </e>
<e> <s>INIT</s> <in>tman3</in> <out>tman3</out> </e>
<!-- n5 errors.
   Text prints guttural nasal as n with macron.
   Digitization of lsr0_refs shows this (incorrectly) as n5
   There are 144 matches with n5 before g or k.
   These n5 to transcode to ṅ
<e> <s>INIT</s> <in></in> <out></out> </e>
<e> <s>INIT</s> <in></in> <out></out> </e>
-->
<e> <s>INIT</s> <in>n5k</in> <out>ṅk</out> </e>
<e> <s>INIT</s> <in>n5g</in> <out>ṅg</out> </e>
<e> <s>INIT</s> <in>n5m</in> <out>ṅm</out> </e>
<e> <s>INIT</s> <in>n5-m</in> <out>ṅ-m</out> </e>
<e> <s>INIT</s> <in>udan5-</in> <out>udaṅ-</out> </e>  <!-- mukha -->
<e> <s>INIT</s> <in>{@an5-</in> <out>{@aṅ-</out> </e>
<e> <s>INIT</s> <in>{@n5,@}</in> <out>{@ṅ,@}</out> </e>
<e> <s>INIT</s> <in>{@n5;@}</in> <out>{@ṅ;@}</out> </e>
<e> <s>INIT</s> <in>man5.@}</in> <out>man5.@}</out> </e>  <!-- homonym -->
<e> <s>INIT</s> <in>man5;@}</in> <out>man5;@}</out> </e>  <!-- homonym -->
<e> <s>INIT</s> <in>tman5,@}</in> <out>tman5,@}</out> </e> <!-- homonym -->
<e> <s>INIT</s> <in>an5 n</in> <out>aṅ n</out> </e>


</fsm>
